elastic_models/__init__.py
elastic_models/access.cpython-312-x86_64-linux-gnu.so
elastic_models/checkpoint_loader.py
elastic_models/device_utils.py
elastic_models/entry.py
elastic_models/errors.py
elastic_models/logger.py
elastic_models/patching_utils.py
elastic_models/cli/__init__.py
elastic_models/cli/base.py
elastic_models/cli/registry.py
elastic_models/cli/serve.py
elastic_models/diffusers/__init__.py
elastic_models/diffusers/pipeline.py
elastic_models/diffusers/pipelines/__init__.py
elastic_models/diffusers/pipelines/flux.py
elastic_models/diffusers/pipelines/mochi.py
elastic_models/diffusers/pipelines/stable_diffusion_xl.py
elastic_models/inference/__init__.py
elastic_models/inference/adapters.py
elastic_models/inference/base.py
elastic_models/inference/compiler.py
elastic_models/inference/cuda_graph.py
elastic_models/inference/errors.py
elastic_models/inference/nvidia/__init__.py
elastic_models/inference/nvidia/iobinders.py
elastic_models/inference/nvidia/memory_allocation.py
elastic_models/inference/nvidia/session.py
elastic_models/inference/nvidia/utils.py
elastic_models/pyarmor_runtime_008031/__init__.py
elastic_models/pyarmor_runtime_008031/pyarmor_runtime.so
elastic_models/serve/__init__.py
elastic_models/serve/build.py
elastic_models/serve/metadata_server.py
elastic_models/serve/server.py
elastic_models/serve/diffusion/__init__.py
elastic_models/serve/diffusion/client.py
elastic_models/serve/diffusion/inference.py
elastic_models/serve/diffusion/serve.py
elastic_models/serve/llm/__init__.py
elastic_models/serve/llm/inference.py
elastic_models/serve/llm/serve.py
elastic_models/serve/stt/__init__.py
elastic_models/serve/stt/inference.py
elastic_models/serve/stt/serve.py
elastic_models/serve/vlm/__init__.py
elastic_models/serve/vlm/inference.py
elastic_models/serve/vlm/serve.py
elastic_models/transformers/__init__.py
elastic_models/transformers/attention_utils.py
elastic_models/transformers/cache_utils.py
thestage_elastic_models-0.1.2.dist-info/METADATA
thestage_elastic_models-0.1.2.dist-info/WHEEL
thestage_elastic_models-0.1.2.dist-info/entry_points.txt
thestage_elastic_models-0.1.2.dist-info/top_level.txt
thestage_elastic_models-0.1.2.dist-info/RECORD
thestage_elastic_models-0.1.2.dist-info/licenses/LICENSE
