Metadata-Version: 2.4
Name: thestage-elastic-models
Version: 0.1.2
Summary: Elastic Models from TheStage AI
Author-email: TheStage AI team <hello@thestage.ai>
Classifier: Programming Language :: Python :: 3.10
Classifier: Programming Language :: Python :: 3.11
Classifier: Programming Language :: Python :: 3.12
Requires-Python: >=3.10
License-File: LICENSE
Requires-Dist: qlip_serve_generator==0.1.17
Requires-Dist: torch<2.7.0,>=2.4.0
Requires-Dist: requests
Requires-Dist: wheel
Requires-Dist: huggingface_hub
Requires-Dist: transformers[sentencepiece]==4.52.3
Requires-Dist: diffusers[torch]<=0.33.1,>=0.30.0
Requires-Dist: cupy-cuda12x==13.3.0
Requires-Dist: cuda-python==12.8.0
Requires-Dist: pyOpenSSL>=25.0.0
Requires-Dist: cryptography>=44.0.0
Requires-Dist: numpy<2,>=1.23.5
Requires-Dist: aiohttp
Provides-Extra: nvidia
Requires-Dist: tensorrt==10.6.0.post2; extra == "nvidia"
Requires-Dist: tensorrt-cu12==10.6.0.post2; extra == "nvidia"
Requires-Dist: tensorrt-cu12-bindings==10.6.0.post2; extra == "nvidia"
Requires-Dist: tensorrt-cu12-libs==10.6.0.post2; extra == "nvidia"
Provides-Extra: blackwell
Requires-Dist: tensorrt==10.9.0.34; extra == "blackwell"
Requires-Dist: tensorrt-cu12==10.9.0.34; extra == "blackwell"
Requires-Dist: tensorrt-cu12-bindings==10.9.0.34; extra == "blackwell"
Requires-Dist: tensorrt-cu12-libs==10.9.0.34; extra == "blackwell"
Dynamic: license-file
